dffml_model_scikit/__init__.py
dffml_model_scikit/scikit_base.py
dffml_model_scikit/scikit_models.py
dffml_model_scikit/version.py
tests/__init__.py
tests/test_scikit.py
tests/test_scikit_integration.py
dffml_model_scikit-0.1.0.post0.dist-info/LICENSE
dffml_model_scikit-0.1.0.post0.dist-info/METADATA
dffml_model_scikit-0.1.0.post0.dist-info/WHEEL
dffml_model_scikit-0.1.0.post0.dist-info/entry_points.txt
dffml_model_scikit-0.1.0.post0.dist-info/top_level.txt
dffml_model_scikit-0.1.0.post0.dist-info/RECORD
