Metadata-Version: 2.1
Name: dffml-model-scikit
Version: 0.1.0.post0
Summary: UNKNOWN
Home-page: https://github.com/intel/dffml/blob/master/model/scikit/README.md
Author: Yash Lamba
Author-email: yashlamba2000@gmail.com
Maintainer: John Andersen
Maintainer-email: john.s.andersen@intel.com
License: MIT
Keywords: dffml
Platform: UNKNOWN
Classifier: Development Status :: 3 - Alpha
Classifier: Intended Audience :: Developers
Classifier: License :: OSI Approved :: MIT License
Classifier: Natural Language :: English
Classifier: Operating System :: OS Independent
Classifier: Programming Language :: Python :: 3 :: Only
Classifier: Programming Language :: Python :: 3.7
Classifier: Programming Language :: Python :: Implementation :: CPython
Classifier: Programming Language :: Python :: Implementation :: PyPy
License-File: LICENSE
Requires-Dist: dffml (>=0.4.0)
Requires-Dist: scipy (==1.4.1)
Requires-Dist: scikit-learn (>=0.21.2)
Requires-Dist: joblib (>=0.13.2)
Requires-Dist: pandas (>=0.25.0)
